procesador/otros/Verilog/Modules/Control Unit/ControlUnit.sv
module ControlUnit (
    input logic [6:0] OpCode,           // Código de operación
    input logic [2:0] Funct3,           // Función 3
    input logic [6:0] Funct7,           // Función 7
    output logic ALUASrc,               // Fuente A para la ALU
    output logic ALUBSrc,               // Fuente B para la ALU
    output logic [3:0] ALUOp,           // Operación de la ALU
    output logic [2:0] ImmSrc,          // Fuente de inmediato
    output logic RUWr,                  // Señal de escritura en el registro
    output logic [4:0] BrOp,            // Señal de operación de Branch
    output logic [2:0] DMCtrl,          // Control de la Data Memory
    output logic DMWr,                  // Señal de escritura en la Data Memory
    output logic [1:0] RUDataWrSrc     // Fuente de datos para escritura en el registro
);

    always @(*) begin
        case (OpCode)
            7'b0110011: begin // Tipo R

            if (Funct7 == 7'b0000001 && Funct3 == 3'b000) begin
          		ALUOp = 4'b1110; // Multiplicación
        	end 
          	else begin
            	ALUOp = {Funct7[5], Funct3[2:0]};
        	end


                RUWr = 1'b1;                 // Habilitar escritura en el registro
                ALUASrc = 1'b0;              // Fuente A proviene del registro
                ALUBSrc = 1'b0;              // Fuente B proviene del registro
                //ALUOp = {Funct7[5], Funct3}; // Operación basada en Funct7 y Funct3
                ImmSrc = 3'bxxx;             // Sin inmediato
                BrOp = 5'b00xxx;             // No operación de salto
                DMWr = 1'b0;                 // No se escribe en memoria
                DMCtrl = 3'bxxx;             // Sin control de memoria
                RUDataWrSrc = 2'b00;         // Datos desde la ALU
            end

            7'b0010011: begin // Tipo I
                RUWr = 1'b1;                 // Escritura en el registro
                ALUASrc = 1'b0;              // Fuente A del registro
                ALUBSrc = 1'b1;              // Fuente B es inmediato
                ImmSrc = 3'b000;             // Inmediato de tipo I
                BrOp = 5'b00xxx;             // No operación de salto
                ALUOp = (Funct3 == 3'b101) ? {Funct7[5], Funct3} : {1'b0, Funct3};
                DMWr = 1'b0;                 // No se escribe en memoria
                DMCtrl = 3'bxxx;             // Sin control de memoria
                RUDataWrSrc = 2'b00;         // Datos desde la ALU
            end

            7'b0000011: begin // Tipo L (Load)
                RUWr = 1'b1;                 // Escritura en el registro
                ALUASrc = 1'b0;              // Fuente A del registro
                ALUBSrc = 1'b1;              // Fuente B es inmediato
                ImmSrc = 3'b000;             // Inmediato de tipo I
                ALUOp = 4'b0000;             // Suma para dirección de memoria
                BrOp = 5'b00xxx;             // No operación de salto
                DMWr = 1'b0;                 // No se escribe en memoria
                DMCtrl = Funct3;             // Control de memoria basado en Funct3
                RUDataWrSrc = 2'b01;         // Datos desde la memoria
            end

            7'b0100011: begin // Tipo S (Store)
                RUWr = 1'b0;                 // Sin escritura en el registro
                ALUASrc = 1'b0;              // Fuente A del registro
                ALUBSrc = 1'b1;              // Fuente B es inmediato
                ImmSrc = 3'b001;             // Inmediato de tipo S
                ALUOp = 4'b0000;             // Suma para dirección de memoria
                BrOp = 5'b00xxx;             // No operación de salto
                DMWr = 1'b1;                 // Habilitar escritura en memoria
                DMCtrl = Funct3;             // Control de memoria basado en Funct3
                RUDataWrSrc = 2'bxx;         // Sin datos para el registro
            end

            7'b1100011: begin // Tipo B (Branch)
                RUWr = 1'b0;                 // Sin escritura en el registro
                ALUASrc = 1'b1;              // Fuente A es inmediato
                ALUBSrc = 1'b1;              // Fuente B es inmediato
                ImmSrc = 3'b101;             // Inmediato de tipo B
                ALUOp = 4'b0000;             // Suma para cálculo de dirección
                BrOp = {2'b01, Funct3};      // Operación de salto según Funct3
                DMWr = 1'b0;                 // No se escribe en memoria
                DMCtrl = 3'bxxx;             // Sin control de memoria
                RUDataWrSrc = 2'bxx;         // Sin datos para el registro
            end

            7'b1101111: begin // Tipo J (JAL)
                RUWr = 1'b1;                 // Escritura en el registro
                ALUASrc = 1'b1;              // Fuente A es PC
                ALUBSrc = 1'b1;              // Fuente B es inmediato
                ImmSrc = 3'b110;             // Inmediato de tipo J
                ALUOp = 4'b0000;             // Suma para cálculo de dirección
                BrOp = 5'b1xxxx;             // Operación de salto
                DMWr = 1'b0;                 // No se escribe en memoria
                DMCtrl = 3'bxxx;             // Sin control de memoria
                RUDataWrSrc = 2'b10;         // Datos desde PC + 4
            end

            7'b1100111: begin // Tipo JR (JALR)
                RUWr = 1'b1;                 // Escritura en el registro
                ALUASrc = 1'b0;              // Fuente A del registro
                ALUBSrc = 1'b1;              // Fuente B es inmediato
                ImmSrc = 3'b000;             // Inmediato de tipo I
                ALUOp = 4'b0000;             // Suma para dirección de salto
                BrOp = 5'b1xxxx;             // Operación de salto
                DMWr = 1'b0;                 // No se escribe en memoria
                DMCtrl = 3'bxxx;             // Sin control de memoria
                RUDataWrSrc = 2'b10;         // Datos desde PC + 4
            end

            7'b0110111: begin // Tipo U (LUI)
                RUWr = 1'b1;                 // Escritura en el registro
                ALUASrc = 1'bx;              // Fuente A no importa
                ALUBSrc = 1'b1;              // Fuente B es inmediato
                ImmSrc = 3'b010;             // Inmediato de tipo U
                ALUOp = 4'b1111;             // Operación especial para LUI
                BrOp = 5'b00xxx;             // No operación de salto
                DMWr = 1'b0;                 // No se escribe en memoria
                DMCtrl = 3'bxxx;             // Sin control de memoria
                RUDataWrSrc = 2'b00;         // Datos desde ALU
            end

            7'b0010111: begin // Tipo U (AUIPC)
                RUWr = 1'b1;                 // Escritura en el registro
                ALUASrc = 1'b1;              // Fuente A es PC
                ALUBSrc = 1'b1;              // Fuente B es inmediato
                ImmSrc = 3'b010;             // Inmediato de tipo U
                ALUOp = 4'b1111;             // Operación especial para AUIPC
                BrOp = 5'b00xxx;             // No operación de salto
                DMWr = 1'b0;                 // No se escribe en memoria
                DMCtrl = 3'bxxx;             // Sin control de memoria
                RUDataWrSrc = 2'b00;         // Datos desde ALU
            end

            default: begin // Caso por defecto
                RUWr = 1'b0;                 // Sin escritura en el registro
                ALUASrc = 1'bx;              // Fuente A no importa
                ALUBSrc = 1'bx;              // Fuente B no importa
                ImmSrc = 3'bxxx;             // Sin inmediato
                ALUOp = 4'bxxxx;             // Sin operación
                BrOp = 5'b00xxx;             // Sin operación de salto
                DMWr = 1'b0;                 // No se escribe en memoria
                DMCtrl = 3'bxxx;             // Sin control de memoria
                RUDataWrSrc = 2'b00;         // Fuente de datos predeterminada
            end
        endcase
    end
endmodule

procesador/otros/Verilog/Modules/Control Unit/CU_tb.sv
`include "ControlUnit.sv"

module CU_tb;

    // Entradas
    logic [6:0] OpCode;
    logic [2:0] Funct3;
    logic [6:0] Funct7;

    // Salidas
    logic ALUASrc;
    logic ALUBSrc;
    logic [3:0] ALUOp;
    logic [2:0] ImmSrc;
    logic RUWr;
    logic [4:0] BrOp;
    logic [2:0] DMCtrl;
    logic DMWr;
    logic [1:0] RUDataWrSrc;

    // Instanciar la unidad de control
    ControlUnit cu (
        .OpCode(OpCode),
        .Funct3(Funct3),
        .Funct7(Funct7),
        .ALUASrc(ALUASrc),
        .ALUBSrc(ALUBSrc),
        .ALUOp(ALUOp),
        .ImmSrc(ImmSrc),
        .RUWr(RUWr),
        .BrOp(BrOp),
        .DMCtrl(DMCtrl),
        .DMWr(DMWr),
        .RUDataWrSrc(RUDataWrSrc)
    );

    initial begin
        $dumpfile("CU.vcd");
        $dumpvars(0, CU_tb);
        // Test 1: Tipo R
        OpCode = 7'b0110011; Funct3 = 3'b000; Funct7 = 7'b0000000;
        #10; 
        $display("Tipo R: RUWr=%b, ALUASrc=%b, ALUBSrc=%b, ALUOp=%b, ImmSrc=%b, DMWr=%b, BrOp=%b, DMCtrl=%b", RUWr, ALUASrc, ALUBSrc, ALUOp, ImmSrc, DMWr, BrOp, DMCtrl);

        // Test 2: Tipo I
        OpCode = 7'b0010011; Funct3 = 3'b010; Funct7 = 7'b0000000;
        #10; 
        $display("Tipo I: RUWr=%b, ALUASrc=%b, ALUBSrc=%b, ALUOp=%b, ImmSrc=%b, DMWr=%b, BrOp=%b, DMCtrl=%b", RUWr, ALUASrc, ALUBSrc, ALUOp, ImmSrc, DMWr, BrOp, DMCtrl);

        // Test 3: Tipo Load
        OpCode = 7'b0000011; Funct3 = 3'b010; Funct7 = 7'b0000000;
        #10; 
        $display("Tipo Load: RUWr=%b, ALUASrc=%b, ALUBSrc=%b, ALUOp=%b, ImmSrc=%b, DMWr=%b, BrOp=%b, DMCtrl=%b", RUWr, ALUASrc, ALUBSrc, ALUOp, ImmSrc, DMWr, BrOp, DMCtrl);

        // Test 4: Tipo Store
        OpCode = 7'b0100011; Funct3 = 3'b010; Funct7 = 7'b0000000;
        #10; 
        $display("Tipo Store: RUWr=%b, ALUASrc=%b, ALUBSrc=%b, ALUOp=%b, ImmSrc=%b, DMWr=%b, BrOp=%b, DMCtrl=%b", RUWr, ALUASrc, ALUBSrc, ALUOp, ImmSrc, DMWr, BrOp, DMCtrl);

        // Test 5: Tipo Branch
        OpCode = 7'b1100011; Funct3 = 3'b000; Funct7 = 7'b0000000;
        #10; 
        $display("Tipo Branch: RUWr=%b, ALUASrc=%b, ALUBSrc=%b, ALUOp=%b, ImmSrc=%b, DMWr=%b, BrOp=%b, DMCtrl=%b", RUWr, ALUASrc, ALUBSrc, ALUOp, ImmSrc, DMWr, BrOp, DMCtrl);

        // Test 6: Tipo J (JAL)
        OpCode = 7'b1101111; Funct3 = 3'b000; Funct7 = 7'b0000000;
        #10; 
        $display("Tipo J: RUWr=%b, ALUASrc=%b, ALUBSrc=%b, ALUOp=%b, ImmSrc=%b, DMWr=%b, BrOp=%b, DMCtrl=%b", RUWr, ALUASrc, ALUBSrc, ALUOp, ImmSrc, DMWr, BrOp, DMCtrl);

        // Test 7: Tipo U (LUI)
        OpCode = 7'b0110111; Funct3 = 3'b000; Funct7 = 7'b0000000;
        #10; 
        $display("Tipo U: RUWr=%b, ALUASrc=%b, ALUBSrc=%b, ALUOp=%b, ImmSrc=%b, DMWr=%b, BrOp=%b, DMCtrl=%b", RUWr, ALUASrc, ALUBSrc, ALUOp, ImmSrc, DMWr, BrOp, DMCtrl);

        // Test 8: Caso por defecto
        OpCode = 7'b1111111; Funct3 = 3'b111; Funct7 = 7'b1111111;
        #10; 
        $display("Caso por defecto: RUWr=%b, ALUASrc=%b, ALUBSrc=%b, ALUOp=%b, ImmSrc=%b, DMWr=%b, BrOp=%b, DMCtrl=%b", RUWr, ALUASrc, ALUBSrc, ALUOp, ImmSrc, DMWr, BrOp, DMCtrl);

        $finish;
    end
endmodule

procesador/otros/Verilog/Modules/Control Unit/CU.vcd
$date
	Wed Oct 30 15:29:39 2024
$end
$version
	Icarus Verilog
$end
$timescale
	1s
$end
$scope module CU_tb $end
$var wire 1 ! RUWr $end
$var wire 2 " RUDataWrSrc [1:0] $end
$var wire 3 # ImmSrc [2:0] $end
$var wire 1 $ DMWr $end
$var wire 3 % DMCtrl [2:0] $end
$var wire 5 & BrOp [4:0] $end
$var wire 4 ' ALUOp [3:0] $end
$var wire 1 ( ALUBSrc $end
$var wire 1 ) ALUASrc $end
$var reg 3 * Funct3 [2:0] $end
$var reg 7 + Funct7 [6:0] $end
$var reg 7 , OpCode [6:0] $end
$scope module cu $end
$var wire 3 - Funct3 [2:0] $end
$var wire 7 . Funct7 [6:0] $end
$var wire 7 / OpCode [6:0] $end
$var reg 1 ) ALUASrc $end
$var reg 1 ( ALUBSrc $end
$var reg 4 0 ALUOp [3:0] $end
$var reg 5 1 BrOp [4:0] $end
$var reg 3 2 DMCtrl [2:0] $end
$var reg 1 $ DMWr $end
$var reg 3 3 ImmSrc [2:0] $end
$var reg 2 4 RUDataWrSrc [1:0] $end
$var reg 1 ! RUWr $end
$upscope $end
$upscope $end
$enddefinitions $end
#0
$dumpvars
b0 4
bx 3
bx 2
b0xxx 1
b0 0
b110011 /
b0 .
b0 -
b110011 ,
b0 +
b0 *
0)
0(
b0 '
b0xxx &
bx %
0$
bx #
b0 "
1!
$end
#10
b10 '
b10 0
b0 #
b0 3
1(
b10 *
b10 -
b10011 ,
b10011 /
#20
b1 "
b1 4
b10 %
b10 2
b0 '
b0 0
b11 ,
b11 /
#30
bx "
bx 4
1$
b1 #
b1 3
0!
b100011 ,
b100011 /
#40
bx %
bx 2
0$
b1000 &
b1000 1
b101 #
b101 3
1)
b0 *
b0 -
b1100011 ,
b1100011 /
#50
b10 "
b10 4
b1xxxx &
b1xxxx 1
b110 #
b110 3
1!
b1101111 ,
b1101111 /
#60
b0 "
b0 4
b0xxx &
b0xxx 1
b1111 '
b1111 0
b10 #
b10 3
x)
b110111 ,
b110111 /
#70
bx '
bx 0
bx #
bx 3
x(
0!
b1111111 +
b1111111 .
b111 *
b111 -
b1111111 ,
b1111111 /
