procesador/otros/Verilog/Modules/Branch Unit/BranchUnit.sv
module BranchUnit (
    input logic [31:0] o_rs1,        // Entrada de fuente rs1Out
    input logic [31:0] o_rs2,        // Entrada de fuente rs2Out
    input logic [4:0] BrOp,            // Señal de operación de branch
    output logic NextPCSrc             // Señal para seleccionar la siguiente dirección del PC
);

    always @(*) begin
        case (BrOp)
            5'b01000: NextPCSrc = (o_rs1 == o_rs2);  // BEQ: Igualdad
            5'b01001: NextPCSrc = (o_rs1 != o_rs2);  // BNE: Diferencia
            5'b01100: NextPCSrc = ($signed(o_rs1) < $signed(o_rs2));  // BLT: Menor que (con signo)
            5'b01101: NextPCSrc = ($signed(o_rs1) >= $signed(o_rs2)); // BGE: Mayor o igual que (con signo)
            5'b01110: NextPCSrc = (o_rs1 < o_rs2);   // BLT: Menor que (sin signo)
            5'b01111: NextPCSrc = (o_rs1 >= o_rs2);  // BGE: Mayor o igual que (sin signo)
            5'b1xxxx: NextPCSrc = 1'b1;
            default:  NextPCSrc = 1'b0;  // Por defecto no hay salto
        endcase
    end
endmodule

procesador/otros/Verilog/Modules/Data Memory/DataMemory.sv
module DataMemory (
    input logic Clk,                 // Señal de reloj
    input logic [31:0] Address,      // Dirección para la memoria de datos
    input logic [31:0] DataWr,       // Datos a escribir en memoria
    input logic [2:0] DMCtrl,        // Señal de control para determinar el tipo de acceso
    input logic DMWr,                // Señal de habilitación de escritura
    output logic [31:0] DataRd       // Datos leídos de la memoria
);

    // Memoria RAM de 32 bits con tamaño ajustable
    logic [7:0] memory [1023:0];

    // Proceso para leer y escribir en la memoria
    always @* begin
        DataRd = 32'b0;
        case (DMCtrl)
            3'b000: begin // Read a byte
                DataRd = {{24{memory[Address][7]}}, memory[Address]}; // Extend the byte to 32 bits
            end
            3'b001: begin // Read a halfword (16 bits)
                DataRd = {{16{memory[Address + 1][7]}}, memory[Address + 1], memory[Address]};
            end
            3'b010: begin // Read a word (32 bits)
                DataRd = {memory[Address], memory[Address + 1], memory[Address + 2], memory[Address + 3]};
            end
            3'b100: begin
                DataRd[31:0] = {24'b0, memory[Address]}; // lb (U): load byte unsigned     
            end  	
            3'b101: begin 
                DataRd[31:0] = {16'b0, memory[Address + 1], memory[Address]}; // lh (U): load halfword unsigned
            end
            default: begin
                DataRd = 32'b0; // If something goes wrong, return 0
            end
        endcase
    end

    // Write data to memory
    always_ff @(posedge Clk) begin
        if (DMWr) begin
            case (DMCtrl)
                3'b000: // Write byte
                    memory[Address] <= DataWr[7:0]; // Only write the 8 least significant bits
                3'b001: // Write halfword (16 bits)
                    {memory[Address], memory[Address + 1]} <= DataWr[15:0];
                3'b010: // Write word (32 bits)
                    {memory[Address], memory[Address + 1], memory[Address + 2], memory[Address + 3]} <= DataWr;
            endcase
        end
    end
endmodule

procesador/otros/Verilog/Modules/Arithmetic Logic Unit/ArithmeticLogicUnit.sv
module ArithmeticLogicUnit (
    input logic [31:0] A,
    input logic [31:0] B,
    input logic [3:0] ALUOp,
    output logic [31:0] ALURes
);

    always @(*) begin
        case (ALUOp)
            4'b0000: ALURes = A + B; // Suma
            4'b1000: ALURes = A - B; // Resta
            4'b0001: ALURes = A << B[4:0]; // Corrimiento lógico a la izquierda
            4'b0011: ALURes = (A < B) ? 32'b1 : 32'b0; // Comparación sin signo
            4'b0010: ALURes = ($signed(A) < $signed(B)) ? 32'b1 : 32'b0; // Comparación con signo
            4'b0100: ALURes = A ^ B; // XOR
            4'b0101: ALURes = A >> B[4:0]; // Corrimiento lógico a la derecha
            4'b1101: ALURes = A >>> B[4:0]; // Corrimiento aritmético a la derecha
            4'b0110: ALURes = A | B; // OR
            4'b0111: ALURes = A & B; // AND
            4'b1110: ALURes = A * B; // Multiplicación
            
            default: ALURes = 32'b0; // Valor por defecto
        endcase
    end
endmodule

procesador/otros/Verilog/Modules/Registers Unit/RegistersUnit.sv
module RegistersUnit (
    input logic Clk,                         // Señal de reloj
    input logic [4:0] rs1,                   // Dirección del primer registro a leer
    input logic [4:0] rs2,                   // Dirección del segundo registro a leer
    input logic [4:0] rd,                    // Dirección del registro donde escribir
    input logic [31:0] DataWr,               // Dato a escribir en el registro
    input logic RUWr,                        // Señal para habilitar escritura en el registro
    output logic [31:0] o_rs1,            // Dato leído del primer registro
    output logic [31:0] o_rs2,             // Dato leído del segundo registro
    output logic [31:0] reg10                // Valor del registro 10
);

    // Array de 32 registros de 32 bits
    logic [31:0] registers [31:0];

    initial begin 
        for(int i = 0; i < 32; i = i + 1) begin
            registers[i] = 32'b0;
        end
        registers[2] = 32'd1024;
    end

    // Lectura de registros
    assign o_rs1 = registers[rs1];
    assign o_rs2 = registers[rs2];
    assign reg10 = registers[10]; // Exponer el contenido del registro 10

    // Escritura en el registro
    always_ff @(posedge Clk) begin
        if (RUWr && rd != 5'b00000) begin
            registers[rd] <= DataWr;        // Escribe el dato en el registro especificado, excepto en x0
        end
    end

endmodule

procesador/otros/Verilog/Modules/Immediate Generator/ImmediateGenerator.sv
module ImmediateGenerator (
    input logic [24:0] Imm,          // Parte superior del inmediato de 25 bits
    input logic [2:0] ImmSrc,        // Selección de inmediato
    output logic [31:0] ImmExt       // Inmediato extendido a 32 bits
);

    always @(*) begin
        case (ImmSrc)
            3'b000: ImmExt = {{20{Imm[24]}}, Imm[24:13]}; // I-Type 
            3'b001: ImmExt = {{20{Imm[24]}}, Imm[24:18], Imm[4:0]}; // S-Type 
            3'b101: ImmExt = {{19{Imm[24]}}, Imm[24], Imm[0], Imm[23:18], Imm[4:1], 1'b0}; // B-Type 
            3'b010: ImmExt = {Imm[24:5], 12'b0}; // U-Type 
            3'b110: ImmExt = {{12{Imm[24]}}, Imm[24], Imm[12:5], Imm[13], Imm[23:14], 1'b0}; // J-Type
            default: ImmExt = 32'b0; // Default value
        endcase
    end
endmodule

procesador/otros/Verilog/Modules/Control Unit/ControlUnit.sv
module ControlUnit (
    input logic [6:0] OpCode,           // Código de operación
    input logic [2:0] Funct3,           // Función 3
    input logic [6:0] Funct7,           // Función 7
    output logic ALUASrc,               // Fuente A para la ALU
    output logic ALUBSrc,               // Fuente B para la ALU
    output logic [3:0] ALUOp,           // Operación de la ALU
    output logic [2:0] ImmSrc,          // Fuente de inmediato
    output logic RUWr,                  // Señal de escritura en el registro
    output logic [4:0] BrOp,            // Señal de operación de Branch
    output logic [2:0] DMCtrl,          // Control de la Data Memory
    output logic DMWr,                  // Señal de escritura en la Data Memory
    output logic [1:0] RUDataWrSrc     // Fuente de datos para escritura en el registro
);

    always @(*) begin
        case (OpCode)
            7'b0110011: begin // Tipo R

            if (Funct7 == 7'b0000001 && Funct3 == 3'b000) begin
          		ALUOp = 4'b1110; // Multiplicación
        	end 
          	else begin
            	ALUOp = {Funct7[5], Funct3[2:0]};
        	end


                RUWr = 1'b1;                 // Habilitar escritura en el registro
                ALUASrc = 1'b0;              // Fuente A proviene del registro
                ALUBSrc = 1'b0;              // Fuente B proviene del registro
                //ALUOp = {Funct7[5], Funct3}; // Operación basada en Funct7 y Funct3
                ImmSrc = 3'bxxx;             // Sin inmediato
                BrOp = 5'b00xxx;             // No operación de salto
                DMWr = 1'b0;                 // No se escribe en memoria
                DMCtrl = 3'bxxx;             // Sin control de memoria
                RUDataWrSrc = 2'b00;         // Datos desde la ALU
            end

            7'b0010011: begin // Tipo I
                RUWr = 1'b1;                 // Escritura en el registro
                ALUASrc = 1'b0;              // Fuente A del registro
                ALUBSrc = 1'b1;              // Fuente B es inmediato
                ImmSrc = 3'b000;             // Inmediato de tipo I
                BrOp = 5'b00xxx;             // No operación de salto
                ALUOp = (Funct3 == 3'b101) ? {Funct7[5], Funct3} : {1'b0, Funct3};
                DMWr = 1'b0;                 // No se escribe en memoria
                DMCtrl = 3'bxxx;             // Sin control de memoria
                RUDataWrSrc = 2'b00;         // Datos desde la ALU
            end

            7'b0000011: begin // Tipo L (Load)
                RUWr = 1'b1;                 // Escritura en el registro
                ALUASrc = 1'b0;              // Fuente A del registro
                ALUBSrc = 1'b1;              // Fuente B es inmediato
                ImmSrc = 3'b000;             // Inmediato de tipo I
                ALUOp = 4'b0000;             // Suma para dirección de memoria
                BrOp = 5'b00xxx;             // No operación de salto
                DMWr = 1'b0;                 // No se escribe en memoria
                DMCtrl = Funct3;             // Control de memoria basado en Funct3
                RUDataWrSrc = 2'b01;         // Datos desde la memoria
            end

            7'b0100011: begin // Tipo S (Store)
                RUWr = 1'b0;                 // Sin escritura en el registro
                ALUASrc = 1'b0;              // Fuente A del registro
                ALUBSrc = 1'b1;              // Fuente B es inmediato
                ImmSrc = 3'b001;             // Inmediato de tipo S
                ALUOp = 4'b0000;             // Suma para dirección de memoria
                BrOp = 5'b00xxx;             // No operación de salto
                DMWr = 1'b1;                 // Habilitar escritura en memoria
                DMCtrl = Funct3;             // Control de memoria basado en Funct3
                RUDataWrSrc = 2'bxx;         // Sin datos para el registro
            end

            7'b1100011: begin // Tipo B (Branch)
                RUWr = 1'b0;                 // Sin escritura en el registro
                ALUASrc = 1'b1;              // Fuente A es inmediato
                ALUBSrc = 1'b1;              // Fuente B es inmediato
                ImmSrc = 3'b101;             // Inmediato de tipo B
                ALUOp = 4'b0000;             // Suma para cálculo de dirección
                BrOp = {2'b01, Funct3};      // Operación de salto según Funct3
                DMWr = 1'b0;                 // No se escribe en memoria
                DMCtrl = 3'bxxx;             // Sin control de memoria
                RUDataWrSrc = 2'bxx;         // Sin datos para el registro
            end

            7'b1101111: begin // Tipo J (JAL)
                RUWr = 1'b1;                 // Escritura en el registro
                ALUASrc = 1'b1;              // Fuente A es PC
                ALUBSrc = 1'b1;              // Fuente B es inmediato
                ImmSrc = 3'b110;             // Inmediato de tipo J
                ALUOp = 4'b0000;             // Suma para cálculo de dirección
                BrOp = 5'b1xxxx;             // Operación de salto
                DMWr = 1'b0;                 // No se escribe en memoria
                DMCtrl = 3'bxxx;             // Sin control de memoria
                RUDataWrSrc = 2'b10;         // Datos desde PC + 4
            end

            7'b1100111: begin // Tipo JR (JALR)
                RUWr = 1'b1;                 // Escritura en el registro
                ALUASrc = 1'b0;              // Fuente A del registro
                ALUBSrc = 1'b1;              // Fuente B es inmediato
                ImmSrc = 3'b000;             // Inmediato de tipo I
                ALUOp = 4'b0000;             // Suma para dirección de salto
                BrOp = 5'b1xxxx;             // Operación de salto
                DMWr = 1'b0;                 // No se escribe en memoria
                DMCtrl = 3'bxxx;             // Sin control de memoria
                RUDataWrSrc = 2'b10;         // Datos desde PC + 4
            end

            7'b0110111: begin // Tipo U (LUI)
                RUWr = 1'b1;                 // Escritura en el registro
                ALUASrc = 1'bx;              // Fuente A no importa
                ALUBSrc = 1'b1;              // Fuente B es inmediato
                ImmSrc = 3'b010;             // Inmediato de tipo U
                ALUOp = 4'b1111;             // Operación especial para LUI
                BrOp = 5'b00xxx;             // No operación de salto
                DMWr = 1'b0;                 // No se escribe en memoria
                DMCtrl = 3'bxxx;             // Sin control de memoria
                RUDataWrSrc = 2'b00;         // Datos desde ALU
            end

            7'b0010111: begin // Tipo U (AUIPC)
                RUWr = 1'b1;                 // Escritura en el registro
                ALUASrc = 1'b1;              // Fuente A es PC
                ALUBSrc = 1'b1;              // Fuente B es inmediato
                ImmSrc = 3'b010;             // Inmediato de tipo U
                ALUOp = 4'b1111;             // Operación especial para AUIPC
                BrOp = 5'b00xxx;             // No operación de salto
                DMWr = 1'b0;                 // No se escribe en memoria
                DMCtrl = 3'bxxx;             // Sin control de memoria
                RUDataWrSrc = 2'b00;         // Datos desde ALU
            end

            default: begin // Caso por defecto
                RUWr = 1'b0;                 // Sin escritura en el registro
                ALUASrc = 1'bx;              // Fuente A no importa
                ALUBSrc = 1'bx;              // Fuente B no importa
                ImmSrc = 3'bxxx;             // Sin inmediato
                ALUOp = 4'bxxxx;             // Sin operación
                BrOp = 5'b00xxx;             // Sin operación de salto
                DMWr = 1'b0;                 // No se escribe en memoria
                DMCtrl = 3'bxxx;             // Sin control de memoria
                RUDataWrSrc = 2'b00;         // Fuente de datos predeterminada
            end
        endcase
    end
endmodule

procesador/otros/Verilog/Modules/Instruction Memory/InstructionMemory.sv
module InstructionMemory (
    input logic [31:0] Address,        // Dirección de la instrucción
    output logic [31:0] Instruction    // Instrucción leída
);

    logic [7:0] memory [0:511];        // Memoria de 8 bits, 512 bytes en total

    // Inicialización de la memoria desde un archivo
    initial begin
        $readmemh("Instructions.txt", memory);
    end

    always @(*) begin
        Instruction = { memory[Address], memory[Address + 1], memory[Address + 2], memory[Address + 3] };
    end
endmodule

procesador/otros/Verilog/Monociclo/Monociclo.sv
`include "../Modules/Instruction Memory/InstructionMemory.sv"
`include "../Modules/Control Unit/ControlUnit.sv"
`include "../Modules/Immediate Generator/ImmediateGenerator.sv"
`include "../Modules/Registers Unit/RegistersUnit.sv"
`include "../Modules/Arithmetic Logic Unit/ArithmeticLogicUnit.sv"
`include "../Modules/Data Memory/DataMemory.sv"
`include "../Modules/Branch Unit/BranchUnit.sv"

module Monociclo (
    input logic Clk
);

    logic [31:0] Instruction;    
    logic [3:0] ALUOp;
    logic ALUASrc;
    logic ALUBSrc;
    logic RUWr;
    logic [2:0] ImmSrc;
    logic [4:0] BrOp;
    logic DMWr;
    logic [2:0] DMCtrl;
    logic [1:0] RUDataWrSrc;
    logic [31:0] ImmExt;
    logic [31:0] o_rs1;
    logic [31:0] o_rs2;
    logic [31:0] reg10;
    logic [31:0] DataWr;
    logic [31:0] i_ALUA;
    logic [31:0] i_ALUB;
    logic [31:0] ALURes;
    logic [31:0] DataRd;
    logic [31:0] NextAddress = 32'b0; // Address + 4
    logic NextPCSrc;
    logic [31:0] NextPC = 32'b0;
    logic [31:0] Address = 32'b0;

    always_ff @(posedge Clk) begin
        Address <= NextPC;
    end

    always @(*) begin
        i_ALUA = ALUASrc ? Address : o_rs1;
        i_ALUB = ALUBSrc ? ImmExt : o_rs2;
        NextAddress = Address + 32'd4;
        NextPC = NextPCSrc ? ALURes : NextAddress;
        DataWr = RUDataWrSrc == 2'b00 ? ALURes : 
                 RUDataWrSrc == 2'b01 ? DataRd : 
                 NextAddress;
    end

    InstructionMemory IM (
        .Address(Address),
        .Instruction(Instruction)
    );

    ControlUnit CU (
        .OpCode(Instruction[6:0]),
        .Funct3(Instruction[14:12]),
        .Funct7(Instruction[31:25]),
        .ALUASrc(ALUASrc),
        .ALUBSrc(ALUBSrc),
        .ALUOp(ALUOp),
        .ImmSrc(ImmSrc),
        .RUWr(RUWr),
        .BrOp(BrOp),
        .DMCtrl(DMCtrl),
        .DMWr(DMWr),
        .RUDataWrSrc(RUDataWrSrc)
    );

    ImmediateGenerator IG (
        .Imm(Instruction[31:7]),
        .ImmSrc(ImmSrc),
        .ImmExt(ImmExt)
    );

    RegistersUnit RU (
        .Clk(Clk),
        .rs1(Instruction[19:15]),
        .rs2(Instruction[24:20]),
        .rd(Instruction[11:7]),
        .DataWr(DataWr),
        .RUWr(RUWr),
        .o_rs1(o_rs1),
        .o_rs2(o_rs2),
        .reg10(reg10)
    );

    ArithmeticLogicUnit ALU (
        .A(i_ALUA),
        .B(i_ALUB),
        .ALUOp(ALUOp),
        .ALURes(ALURes)
    );  

    DataMemory DM (
        .Clk(Clk),
        .Address(ALURes),
        .DataWr(o_rs2),
        .DMCtrl(DMCtrl),
        .DMWr(DMWr),
        .DataRd(DataRd)
    );

    BranchUnit BU (
        .o_rs1(o_rs1),
        .o_rs2(o_rs2),
        .BrOp(BrOp),
        .NextPCSrc(NextPCSrc)
    );

endmodule

procesador/otros/Verilog/Monociclo/Monociclo_tb.sv
`include "Monociclo.sv"

module Monociclo_tb;
    logic Clk;
    integer instruction_count = 0; // Cambiado a `integer` para compatibilidad
    integer file;                 // Variable para manejar el archivo

    // Instancia del módulo Monociclo
    Monociclo MC (
        .Clk(Clk)
    );

    // Generación de reloj
    always #5 Clk = ~Clk;

    // Bloque inicial
    initial begin
        Clk = 0;

        // Abrir el archivo para escritura
        file = $fopen("Monociclo_output.txt", "w");
        if (file == 0) begin
            $display("Error: No se pudo abrir el archivo Monociclo_output.txt.");
            $finish; // Detener simulación si no se puede abrir el archivo
        end

        // Configuración de dumping de señales
        $dumpfile("Monociclo.vcd");
        $dumpvars(0, Monociclo_tb);

        // Primera instrucción
        instruction_count++;
        $display("\n%d instrucción\n", instruction_count);
        $fwrite(file, "\n%d instrucción\n", instruction_count);

        #6000;
        $fclose(file); // Cerrar el archivo al finalizar
        $finish;
    end

    // Monitor de señales
    initial begin
        $monitor(
            "Time: %0t\nInstruction: %h\nALUOp: %h\nALUASrc: %b\n\nALUBSrc: %b\nRUWr: %b\nImmSrc: %h\n\nBrOp: %h\nDMWr: %b\nDMCtrl: %h\n\nRUDataWrSrc: %h\nImmExt: %h\no_rs1: %h\n\no_rs2: %h\nDataWr: %h\ni_ALUA: %h\n\ni_ALUB: %h\nALURes: %h\n\nDataRd: %h\nNextAddress: %h\nNextPCSrc: %b\n\nNextPC: %h\nAddress: %h\nreg10: %h\n",
            $time, MC.Instruction, MC.ALUOp, MC.ALUASrc, MC.ALUBSrc, MC.RUWr, MC.ImmSrc, MC.BrOp, MC.DMWr, MC.DMCtrl, MC.RUDataWrSrc, MC.ImmExt, MC.o_rs1, MC.o_rs2, MC.DataWr, MC.i_ALUA, MC.i_ALUB, MC.ALURes, MC.DataRd, MC.NextAddress, MC.NextPCSrc, MC.NextPC, MC.Address, MC.reg10
        );
    end

    // Escribir señales en archivo en cada flanco de reloj
    always @(posedge Clk) begin
        instruction_count++;
        $display("\n%d instrucción\n", instruction_count);
        $fwrite(file, "\n%d instrucción\n", instruction_count);
        $fwrite(file, "Time: %0t\nInstruction: %h\nALUOp: %h\nALUASrc: %b\n\nALUBSrc: %b\nRUWr: %b\nImmSrc: %h\n\nBrOp: %h\nDMWr: %b\nDMCtrl: %h\n\nRUDataWrSrc: %h\nImmExt: %h\no_rs1: %h\n\no_rs2: %h\nDataWr: %h\ni_ALUA: %h\n\ni_ALUB: %h\nALURes: %h\n\nDataRd: %h\nNextAddress: %h\nNextPCSrc: %b\n\nNextPC: %h\nAddress: %h\nreg10: %h\n\n",
                 $time, MC.Instruction, MC.ALUOp, MC.ALUASrc, MC.ALUBSrc, MC.RUWr, MC.ImmSrc, MC.BrOp, MC.DMWr, MC.DMCtrl, MC.RUDataWrSrc, MC.ImmExt, MC.o_rs1, MC.o_rs2, MC.DataWr, MC.i_ALUA, MC.i_ALUB, MC.ALURes, MC.DataRd, MC.NextAddress, MC.NextPCSrc, MC.NextPC, MC.Address, MC.reg10);
    end
endmodule

procesador/otros/Verilog/Monociclo/Monociclo.vcd
$date
	Fri Nov 22 20:14:59 2024
$end
$version
	Icarus Verilog
$end
$timescale
	1s
$end
$scope module Monociclo_tb $end
$var reg 1 ! Clk $end
$var integer 32 " file [31:0] $end
$var integer 32 # instruction_count [31:0] $end
$scope module MC $end
$var wire 1 ! Clk $end
$var wire 32 $ reg10 [31:0] $end
$var wire 32 % o_rs2 [31:0] $end
$var wire 32 & o_rs1 [31:0] $end
$var wire 1 ' RUWr $end
$var wire 2 ( RUDataWrSrc [1:0] $end
$var wire 1 ) NextPCSrc $end
$var wire 32 * Instruction [31:0] $end
$var wire 3 + ImmSrc [2:0] $end
$var wire 32 , ImmExt [31:0] $end
$var wire 32 - DataRd [31:0] $end
$var wire 1 . DMWr $end
$var wire 3 / DMCtrl [2:0] $end
$var wire 5 0 BrOp [4:0] $end
$var wire 32 1 ALURes [31:0] $end
$var wire 4 2 ALUOp [3:0] $end
$var wire 1 3 ALUBSrc $end
$var wire 1 4 ALUASrc $end
$var reg 32 5 Address [31:0] $end
$var reg 32 6 DataWr [31:0] $end
$var reg 32 7 NextAddress [31:0] $end
$var reg 32 8 NextPC [31:0] $end
$var reg 32 9 i_ALUA [31:0] $end
$var reg 32 : i_ALUB [31:0] $end
$scope module ALU $end
$var wire 32 ; A [31:0] $end
$var wire 32 < B [31:0] $end
$var wire 4 = ALUOp [3:0] $end
$var reg 32 > ALURes [31:0] $end
$upscope $end
$scope module BU $end
$var wire 32 ? o_rs2 [31:0] $end
$var wire 32 @ o_rs1 [31:0] $end
$var wire 5 A BrOp [4:0] $end
$var reg 1 ) NextPCSrc $end
$upscope $end
$scope module CU $end
$var wire 3 B Funct3 [2:0] $end
$var wire 7 C Funct7 [6:0] $end
$var wire 7 D OpCode [6:0] $end
$var reg 1 4 ALUASrc $end
$var reg 1 3 ALUBSrc $end
$var reg 4 E ALUOp [3:0] $end
$var reg 5 F BrOp [4:0] $end
$var reg 3 G DMCtrl [2:0] $end
$var reg 1 . DMWr $end
$var reg 3 H ImmSrc [2:0] $end
$var reg 2 I RUDataWrSrc [1:0] $end
$var reg 1 ' RUWr $end
$upscope $end
$scope module DM $end
$var wire 32 J Address [31:0] $end
$var wire 1 ! Clk $end
$var wire 3 K DMCtrl [2:0] $end
$var wire 1 . DMWr $end
$var wire 32 L DataWr [31:0] $end
$var reg 32 M DataRd [31:0] $end
$upscope $end
$scope module IG $end
$var wire 25 N Imm [24:0] $end
$var wire 3 O ImmSrc [2:0] $end
$var reg 32 P ImmExt [31:0] $end
$upscope $end
$scope module IM $end
$var wire 32 Q Address [31:0] $end
$var reg 32 R Instruction [31:0] $end
$upscope $end
$scope module RU $end
$var wire 1 ! Clk $end
$var wire 32 S DataWr [31:0] $end
$var wire 1 ' RUWr $end
$var wire 32 T o_rs1 [31:0] $end
$var wire 32 U o_rs2 [31:0] $end
$var wire 5 V rd [4:0] $end
$var wire 32 W reg10 [31:0] $end
$var wire 5 X rs1 [4:0] $end
$var wire 5 Y rs2 [4:0] $end
$scope begin $ivl_for_loop0 $end
$var integer 32 Z i [31:0] $end
$upscope $end
$upscope $end
$upscope $end
$upscope $end
$enddefinitions $end
$comment Show the parameter values. $end
$dumpall
$end
#0
$dumpvars
b100000 Z
b0 Y
b10 X
b0 W
b10 V
b0 U
b10000000000 T
b1111100000 S
b11111110000000010000000100010011 R
b0 Q
b11111111111111111111111111100000 P
b0 O
b1111111000000001000000010 N
b0 M
b0 L
bx K
b1111100000 J
b0 I
b0 H
bx G
b0xxx F
b0 E
b10011 D
b1111111 C
b0 B
b0xxx A
b10000000000 @
b0 ?
b1111100000 >
b0 =
b11111111111111111111111111100000 <
b10000000000 ;
b11111111111111111111111111100000 :
b10000000000 9
b100 8
b100 7
b1111100000 6
b0 5
04
13
b0 2
b1111100000 1
b0xxx 0
bx /
0.
b0 -
b11111111111111111111111111100000 ,
b0 +
b11111110000000010000000100010011 *
0)
b0 (
1'
b10000000000 &
b0 %
b0 $
b1 #
b10000000000000000000000000000011 "
0!
$end
#5
b11100 :
b11100 <
bx -
bx M
b11100 ,
b11100 P
bx (
bx I
b10 /
b10 G
b10 K
1.
b1 +
b1 H
b1 O
0'
bx 6
bx S
b11100 V
b1 Y
b10001001011100 N
b0 C
b10 B
b100011 D
b1111111100 1
b1111111100 >
b1111111100 J
b100010010111000100011 *
b100010010111000100011 R
b1000 8
b1000 7
b1111100000 9
b1111100000 ;
b1111100000 &
b1111100000 @
b1111100000 T
b100 5
b100 Q
b10 #
1!
#10
0!
#15
b1111111000 1
b1111111000 >
b1111111000 J
b11000 :
b11000 <
b11000 ,
b11000 P
b11000 V
b1000 Y
b10000001001011000 N
b100000010010110000100011 *
b100000010010110000100011 R
bx 6
bx S
b1100 8
b1100 7
bx -
bx M
b1000 5
b1000 Q
b11 #
1!
#20
0!
#25
b10000000000 1
b10000000000 >
b10000000000 J
b100000 :
b100000 <
b100000 ,
b100000 P
b0 (
b0 I
bx /
bx G
bx K
0.
b0 +
b0 H
b0 O
1'
b10000000000 6
b10000000000 S
b1000 V
b0 Y
b1000000001000001000 N
b1 C
b0 B
b10011 D
b0 -
b0 M
b10000000010000010000010011 *
b10000000010000010000010011 R
b10000 8
b10000 7
b1100 5
b1100 Q
b100 #
1!
#30
0!
#35
b1010 6
b1010 S
b1010 1
b1010 >
b1010 J
b1010 :
b1010 <
b0 9
b0 ;
b1010 ,
b1010 P
b1111 V
b1010 Y
b0 &
b0 @
b0 T
b0 X
b10100000000001111 N
b0 C
b101000000000011110010011 *
b101000000000011110010011 R
b10100 8
b10100 7
b10000 5
b10000 Q
b101 #
1!
#40
0!
#45
b1111101100 1
b1111101100 >
b1111101100 J
bx -
bx M
bx 6
bx S
b11111111111111111111111111101100 :
b11111111111111111111111111101100 <
b10000000000 9
b10000000000 ;
b11111111111111111111111111101100 ,
b11111111111111111111111111101100 P
bx (
bx I
b10 /
b10 G
b10 K
1.
b1 +
b1 H
b1 O
0'
b1100 V
b1010 %
b1010 ?
b1010 L
b1010 U
b1111 Y
b10000000000 &
b10000000000 @
b10000000000 T
b1000 X
b1111111011110100001001100 N
b1111111 C
b10 B
b100011 D
b11111110111101000010011000100011 *
b11111110111101000010011000100011 R
b11000 8
b11000 7
b10100 5
b10100 Q
b110 #
1!
#50
0!
#55
b1 (
b1 I
0.
b0 +
b0 H
b0 O
1'
b1110 V
b0 %
b0 ?
b0 L
b0 U
b1100 Y
b1111111011000100001001110 N
b11 D
b11111110110001000010011100000011 *
b11111110110001000010011100000011 R
b1010 6
b1010 S
b11100 8
b11100 7
b1010 -
b1010 M
b11000 5
b11000 Q
b111 #
1!
#60
0!
#65
b1 1
b1 >
b1 J
b0 -
b0 M
b1 6
b1 S
b1 :
b1 <
b0 9
b0 ;
b1 ,
b1 P
b0 (
b0 I
bx /
bx G
bx K
b1111 V
b1 Y
b0 &
b0 @
b0 T
b0 X
b10000000001111 N
b0 C
b0 B
b10011 D
b100000000011110010011 *
b100000000011110010011 R
b100000 8
b100000 7
b11100 5
b11100 Q
b1000 #
1!
#70
0!
#75
b101100 1
b101100 >
b101100 J
b0x0xx00 6
b0x0xx00 S
b1100 :
b1100 <
b100000 9
b100000 ;
1)
b1100 ,
b1100 P
bx (
bx I
b1100 0
b1100 A
b1100 F
b101 +
b101 H
b101 O
14
0'
b1100 V
b1010 %
b1010 ?
b1010 L
b1010 U
b1110 Y
b1 &
b1 @
b1 T
b1111 X
b11100111110001100 N
b100 B
b1100011 D
b111001111100011001100011 *
b111001111100011001100011 R
b101100 8
b100100 7
b100000 5
b100000 Q
b1001 #
1!
#80
0!
#85
b1 :
b1 <
0)
b1 ,
b1 P
b0 (
b0 I
b0xxx 0
b0xxx A
b0xxx F
b0 +
b0 H
b0 O
04
1'
b110000 8
b1111 V
b0 %
b0 ?
b0 L
b0 U
b1 Y
b0 &
b0 @
b0 T
b0 X
b10000000001111 N
b0 B
b10011 D
b1 1
b1 >
b1 J
b100000000011110010011 *
b100000000011110010011 R
b1 6
b1 S
b110000 7
b0 9
b0 ;
b101100 5
b101100 Q
b1010 #
1!
#90
0!
#95
b1111101000 1
b1111101000 >
b1111101000 J
bx -
bx M
bx 6
bx S
b11111111111111111111111111101000 :
b11111111111111111111111111101000 <
b10000000000 9
b10000000000 ;
b11111111111111111111111111101000 ,
b11111111111111111111111111101000 P
bx (
bx I
b10 /
b10 G
b10 K
1.
b1 +
b1 H
b1 O
0'
b1000 V
b1 %
b1 ?
b1 L
b1 U
b1111 Y
b10000000000 &
b10000000000 @
b10000000000 T
b1000 X
b1111111011110100001001000 N
b1111111 C
b10 B
b100011 D
b11111110111101000010010000100011 *
b11111110111101000010010000100011 R
b110100 8
b110100 7
b110000 5
b110000 Q
b1011 #
1!
#100
0!
#105
b100000 :
b100000 <
b1010100 1
b1010100 >
b1010100 J
1)
b100000 ,
b100000 P
b10 (
b10 I
bx /
bx G
bx K
0.
b1xxxx 0
b1xxxx A
b1xxxx F
b110 +
b110 H
b110 O
14
1'
b111000 6
b111000 S
b110100 9
b110100 ;
b0 V
b0 %
b0 ?
b0 L
b0 U
b0 Y
b0 &
b0 @
b0 T
b0 X
b1000000000000000000 N
b1 C
b0 B
b1101111 D
b0 -
b0 M
b10000000000000000001101111 *
b10000000000000000001101111 R
b1010100 8
b111000 7
b110100 5
b110100 Q
b1100 #
1!
#110
0!
#115
b1010 -
b1010 M
b11111111111111111111111111101100 :
b11111111111111111111111111101100 <
0)
b11111111111111111111111111101100 ,
b11111111111111111111111111101100 P
b1 (
b1 I
b10 /
b10 G
b10 K
b0xxx 0
b0xxx A
b0xxx F
b0 +
b0 H
b0 O
04
b1011000 8
b1110 V
b1100 Y
b10000000000 &
b10000000000 @
b10000000000 T
b1000 X
b1111111011000100001001110 N
b1111111 C
b10 B
b11 D
b1111101100 1
b1111101100 >
b1111101100 J
b11111110110001000010011100000011 *
b11111110110001000010011100000011 R
b1010 6
b1010 S
b1011000 7
b10000000000 9
b10000000000 ;
b1010100 5
b1010100 Q
b1101 #
1!
#120
0!
#125
b1 1
b1 >
b1 J
b0 -
b0 M
b1 6
b1 S
b1 :
b1 <
b0 9
b0 ;
b1 ,
b1 P
b0 (
b0 I
bx /
bx G
bx K
b1111 V
b1 Y
b0 &
b0 @
b0 T
b0 X
b10000000001111 N
b0 C
b0 B
b10011 D
b100000000011110010011 *
b100000000011110010011 R
b1011100 8
b1011100 7
b1011000 5
b1011000 Q
b1110 #
1!
#130
0!
#135
b111000 1
b111000 >
b111000 J
b0xxxx000 6
b0xxxx000 S
b11111111111111111111111111011100 :
b11111111111111111111111111011100 <
b1011100 9
b1011100 ;
1)
b11111111111111111111111111011100 ,
b11111111111111111111111111011100 P
bx (
bx I
b1100 0
b1100 A
b1100 F
b101 +
b101 H
b101 O
14
0'
b11101 V
b1010 %
b1010 ?
b1010 L
b1010 U
b1110 Y
b1 &
b1 @
b1 T
b1111 X
b1111110011100111110011101 N
b1111110 C
b100 B
b1100011 D
b11111100111001111100111011100011 *
b11111100111001111100111011100011 R
b111000 8
b1100000 7
b1011100 5
b1011100 Q
b1111 #
1!
#140
0!
