verilog-eda/branchUnit/Branch_unit.sv
module Branch_unit (
    input  logic [31:0] In1,       // Operando 1
    input  logic [31:0] In2,       // Operando 2
    input  logic  [4:0] BrOp,      // Código de operación de branch
    output logic        NextPCSrc // Señal de salto
);

    //------------------------------------------------------------------------------
    // Lógica combinacional para determinar NextPCSrc
    //------------------------------------------------------------------------------
    always_comb begin
        // Valor por defecto: no salto
        NextPCSrc = 0;

        // Salto incondicional (bit 4 = 1)
        if (BrOp[4]) begin
            NextPCSrc = 1;
        end

        // Opciones de salto condicional (bits [4:3] = 2'b10)
      if (BrOp[4:3] == 01) begin
            unique case (BrOp[3:0])
                4'b1000: NextPCSrc = (In1 == In2);                     // BEQ
                4'b1001: NextPCSrc = (In1 != In2);                     // BNE
                4'b1100: NextPCSrc = (In1 <  In2);                     // BLT (signed)
                4'b1101: NextPCSrc = (In1 >= In2);                     // BGE (signed)
                4'b1110: NextPCSrc = ($unsigned(In1) <  $unsigned(In2)); // BLTU (unsigned)
                4'b1111: NextPCSrc = ($unsigned(In1) >= $unsigned(In2)); // BGEU (unsigned)
                default: NextPCSrc = 1'b0;
            endcase
        end
        if(BrOp[4:3] == 2'b00)begin	//No realiza el salto cuando los 2 bits mas significativos son 00
			NextPCSrc = 0;				//Salida en 0
        end
      
    end

endmodule

verilog-eda/dataMemory/Data_memory.sv
module Data_memory (
    input  logic [31:0] Address,   // Dirección de memoria
    input  logic [31:0] DataWr,    // Datos a escribir
    input  logic        DMWr,      // Señal de escritura
    input  logic [2:0]  DMCtrl,    // Control de acceso
    output logic [31:0] DataRd     // Datos leídos
);

    //------------------------------------------------------------------------------
    // Memoria de bytes (little endian)
    //------------------------------------------------------------------------------
    logic [7:0] Memory [0:31] = '{ default: 8'b0 };

    //------------------------------------------------------------------------------
    // Lectura de memoria (combinacional)
    //------------------------------------------------------------------------------
    always_comb begin
        DataRd = 32'b0;
        unique case (DMCtrl)
            3'b000: // LB: load byte (signed)
                DataRd = {{24{Memory[Address][7]}}, Memory[Address]};
            3'b001: // LH: load halfword (signed)
                DataRd = {{16{Memory[Address+1][7]}}, Memory[Address+1], Memory[Address]};
            3'b010: // LW: load word
                DataRd = {Memory[Address+3], Memory[Address+2], Memory[Address+1], Memory[Address]};
            3'b100: // LBU: load byte unsigned
                DataRd = {24'b0, Memory[Address]};
            3'b101: // LHU: load halfword unsigned
                DataRd = {16'b0, Memory[Address+1], Memory[Address]};
            default:
                DataRd = 32'b0;
        endcase
    end

    //------------------------------------------------------------------------------
    // Escritura de memoria (combinacional con retardo implicito)
    //------------------------------------------------------------------------------
    always_comb begin
        if (DMWr) begin
            unique case (DMCtrl)
                3'b000: // SB: save byte
                    Memory[Address] <= DataWr[7:0];
                3'b001: // SH: save halfword
                begin
                    Memory[Address]     <= DataWr[7:0];
                    Memory[Address + 1] <= DataWr[15:8];
                end
                3'b010: // SW: save word
                begin
                    Memory[Address]     <= DataWr[7:0];
                    Memory[Address + 1] <= DataWr[15:8];
                    Memory[Address + 2] <= DataWr[23:16];
                    Memory[Address + 3] <= DataWr[31:24];
                end
                default: ;
            endcase
        end
    end

endmodule

verilog-eda/alu/ALU.sv
module ALU (
    input  logic [31:0] A,        // Operando A
    input  logic [31:0] B,        // Operando B
    input  logic  [3:0] ALUOp,    // Código de operación
    output logic [31:0] Alu_out   // Resultado
);

    //------------------------------------------------------------------------------
    // Lógica combinacional de la ALU
    //------------------------------------------------------------------------------
    always_comb begin
        unique case (ALUOp)
            4'b0000: Alu_out = A + B;                              // ADD
            4'b1000: Alu_out = A - B;                              // SUB
            4'b0001: Alu_out = A << B[4:0];                        // SLL
            4'b0010: Alu_out = {31'b0, A <  B};                    // SLT (signed)
            4'b0011: Alu_out = {31'b0, $unsigned(A) < $unsigned(B)}; // SLTU (unsigned)
            4'b0100: Alu_out = A ^ B;                              // XOR
            4'b0101: Alu_out = A >> B[4:0];                        // SRL
            4'b1101: Alu_out = A >>> B[4:0];                       // SRA
            4'b0110: Alu_out = A | B;                              // OR
            4'b0111: Alu_out = A & B;                              // AND
            default: Alu_out = 32'b0;                              // NOP
        endcase
    end

endmodule

verilog-eda/Imm/Imm_unit.sv
module Imm_unit (
    input  logic [24:0] ImmIn,    // Bits de inmediato brutos
    input  logic [2:0]  ImmSrc,   // Selección de tipo de inmediato
    output logic [31:0] ImmExt    // Inmediato extendido a 32 bits
);

    //------------------------------------------------------------------------------
    // Extensión de signo
    //------------------------------------------------------------------------------
    always_comb begin
        // Inicialización de ImmExt según signo (bit 24)
        ImmExt = (ImmIn[24]) ? 32'hFFFFFFFF : 32'b0;

        //------------------------------------------------------------------------------
        // Construcción del inmediato según formato
        //------------------------------------------------------------------------------
        unique case (ImmSrc)
            3'b000: begin // I-type
                ImmExt[11:0] = ImmIn[24:13];
            end
            3'b001: begin // S-type
                ImmExt[11:0] = {ImmIn[24:18], ImmIn[4:0]};
            end
            3'b101: begin // B-type
                ImmExt[12:0] = {ImmIn[24], ImmIn[0], ImmIn[23:18], ImmIn[4:1], 1'b0};
            end
            3'b010: begin // U-type
                ImmExt[31:12] = ImmIn[24:5];
            end
            3'b110: begin // J-type
                ImmExt[20:0] = {ImmIn[24], ImmIn[12:5], ImmIn[13], ImmIn[23:14], 1'b0};
            end
            default: ; // Sin cambios más allá de la inicialización
        endcase
    end

endmodule

verilog-eda/registerUnit/Register_unit.sv
module Register_unit (
    input  logic        Clk,       // Señal de reloj
    input  logic [31:0] RuDataWr,  // Datos a escribir
    input  logic [4:0]  Rs1,       // Índice registro fuente 1
    input  logic [4:0]  Rs2,       // Índice registro fuente 2
    input  logic [4:0]  Rd,        // Índice registro destino
    input  logic        RuWr,      // Habilita escritura en registro
    output logic [31:0] RuRs1,     // Dato leído registro fuente 1
    output logic [31:0] RuRs2      // Dato leído registro fuente 2
);

    //------------------------------------------------------------------------------
    // Bancos de registros (32 x 32 bits)
    //------------------------------------------------------------------------------
    logic [31:0] Registers [0:31] = '{ default: 32'b0 };

    //------------------------------------------------------------------------------
    // Escritura de registros (flanco de subida)
    //------------------------------------------------------------------------------
    always_ff @(posedge Clk) begin
        if (RuWr && (Rd != 5'd0)) begin
            Registers[Rd] <= RuDataWr;
        end
    end

    //------------------------------------------------------------------------------
    // Lectura de registros (combinacional)
    //------------------------------------------------------------------------------
    always_comb begin
        RuRs1 = Registers[Rs1];
        RuRs2 = Registers[Rs2];
    end

endmodule

verilog-eda/controlUnit/Control_unit.sv
module Control_unit (
    input  logic [6:0]  OpCode,       // Código de operación
    input  logic [2:0]  Funct3,       // Función 3 bits
    input  logic [6:0]  Funct7,       // Función 7 bits
    output logic        RUWr,        // Registro write enable
    output logic [2:0]  ImmSrc,      // Fuente de inmediato
    output logic        AluASrc,     // ALU A source select
    output logic        AluBSrc,     // ALU B source select
    output logic [4:0]  BrOp,        // Branch operation
    output logic [3:0]  ALUOp,       // ALU operation
    output logic        DMWr,        // Data memory write enable
    output logic [2:0]  DMCtrl,      // Data memory control
    output logic [1:0]  RUDataWrSrc  // Register write data source
);

    //------------------------------------------------------------------------------
    // Señales intermedias y valor por defecto
    //------------------------------------------------------------------------------
    always_comb begin
        // Inicialización de salidas
        RUWr         = 1'b0;
        ImmSrc       = 3'b000;
        AluASrc      = 1'b0;
        AluBSrc      = 1'b0;
        BrOp         = 5'b00000;
        ALUOp        = 4'b0000;
        DMWr         = 1'b0;
        DMCtrl       = 3'b000;
        RUDataWrSrc  = 2'b00;

        //--------------------------------------------------
        // Tipo de instrucción según OpCode
        //--------------------------------------------------
        unique case (OpCode)
            7'b0110011: begin // R-type
                RUWr = 1'b1;
            end
            7'b0010011: begin // I-type (arith)
                RUWr     = 1'b1;
                AluBSrc  = 1'b1;
            end
            7'b0000011: begin // I-type (load)
                RUWr         = 1'b1;
                AluBSrc      = 1'b1;
                RUDataWrSrc  = 2'b01;
            end
            7'b1100111: begin // I-type (jalr)
                RUWr         = 1'b1;
                AluBSrc      = 1'b1;
                BrOp         = 5'b10000;
                RUDataWrSrc  = 2'b10;
            end
            7'b1100011: begin // B-type (branch)
                ImmSrc  = 3'b101;
                AluASrc = 1'b1;
                AluBSrc = 1'b1;
            end
            7'b0100011: begin // S-type (store)
                ImmSrc  = 3'b001;
                AluBSrc = 1'b1;
                DMWr    = 1'b1;
            end
            7'b1101111: begin // J-type (jal)
                RUWr         = 1'b1;
                ImmSrc       = 3'b110;
                AluASrc      = 1'b1;
                AluBSrc      = 1'b1;
                BrOp         = 5'b10000;
                RUDataWrSrc  = 2'b10;
            end
            7'b0110111: begin // U-type (lui)
                RUWr    = 1'b1;
                ImmSrc  = 3'b010;
                AluBSrc = 1'b1;
                ALUOp   = 4'b0111;
            end
            7'b0010111: begin // U-type (auipc)
                RUWr         = 1'b1;
                ImmSrc       = 3'b010;
                AluASrc      = 1'b1;
                AluBSrc      = 1'b1;
                BrOp         = 5'b10000;
                RUDataWrSrc  = 2'b10;
            end
            default: begin
                // mantener valores por defecto
            end
        endcase

        //------------------------------------------------------------------------------
        // ALUOp para R-type
        //------------------------------------------------------------------------------
        if (OpCode == 7'b0110011) begin
            unique case ({Funct3, Funct7})
                10'b0000000000: ALUOp = 4'b0000; // ADD
                10'b0000100000: ALUOp = 4'b1000; // SUB
                10'b0010000000: ALUOp = 4'b0001; // SLL
                10'b0100000000: ALUOp = 4'b0010; // SLT
                10'b0110000000: ALUOp = 4'b0011; // SLTU
                10'b1000000000: ALUOp = 4'b0100; // XOR
                10'b1010000000: ALUOp = 4'b0101; // SRL
                10'b1010100000: ALUOp = 4'b1101; // SRA
                10'b1100000000: ALUOp = 4'b0110; // OR
                10'b1110000000: ALUOp = 4'b0111; // AND
                default:        ALUOp = 4'b0000;
            endcase
        end

        //------------------------------------------------------------------------------
        // ALUOp para I-type arith (addi, slli, ...)
        //------------------------------------------------------------------------------
        if (OpCode == 7'b0010011) begin
            unique case (Funct3)
                3'b000: ALUOp = 4'b0000; // ADDI
                3'b001: ALUOp = 4'b0001; // SLLI
                3'b010: ALUOp = 4'b0010; // SLTI
                3'b011: ALUOp = 4'b0011; // SLTIU
                3'b100: ALUOp = 4'b0100; // XORI
                3'b101: begin            // SRLI/SRAI
                    ALUOp = (Funct7[6]) ? 4'b1101 : 4'b0101;
                end
                3'b110: ALUOp = 4'b0110; // ORI
                3'b111: ALUOp = 4'b0111; // ANDI
                default: ALUOp = 4'b0000;
            endcase
        end

        //------------------------------------------------------------------------------
        // BrOp para B-type condicional
        //------------------------------------------------------------------------------
        if (OpCode == 7'b1100011) begin
            unique case (Funct3)
                3'b000: BrOp = 5'b01000; // BEQ
                3'b001: BrOp = 5'b01001; // BNE
                3'b100: BrOp = 5'b01100; // BLT
                3'b101: BrOp = 5'b01101; // BGE
                3'b110: BrOp = 5'b01110; // BLTU
                3'b111: BrOp = 5'b01111; // BGEU
                default: BrOp = 5'b00000;
            endcase
        end

        //------------------------------------------------------------------------------
        // DMCtrl para loads/stores
        //------------------------------------------------------------------------------
        if (OpCode == 7'b0000011 || OpCode == 7'b0100011) begin
            unique case (Funct3)
                3'b000: DMCtrl = 3'b000; // LB/SB
                3'b001: DMCtrl = 3'b001; // LH/SH
                3'b010: DMCtrl = 3'b010; // LW/SW
                3'b100: DMCtrl = 3'b100; // LBU
                3'b101: DMCtrl = 3'b101; // LHU
                default: DMCtrl = 3'b000;
            endcase
        end
    end

endmodule

verilog-eda/inst_memory/Instruction_memory.sv
module Instruction_memory(
    input  logic [31:0] Address,
    output logic [31:0] Instruction
);
    logic [7:0] Memory[255:0];

    // ⚠️ Leer el archivo .hex (1 byte por línea)
    initial begin
        $readmemh("Instruction_memory.hex", Memory);
    end

    // ✅ Construcción de instrucción en little-endian
    always_comb begin
        Instruction = {Memory[Address+3], Memory[Address+2], Memory[Address+1], Memory[Address]};
    end
endmodule

verilog-eda/Procesador.sv
`include "Control_unit.sv"
`include "Register_unit.sv"
`include "Branch_unit.sv"
`include "ALU.sv"
`include "Data_memory.sv"
`include "Imm_unit.sv"
`include "Instruction_memory.sv"

module Procesador_monociclo (
    input  logic         Clk
);

    // Program Counter and Instruction
    logic [31:0] Out_PC           = 32'b0;
    logic [31:0] Out_Instruction;

    // Control signals
    logic        RUWr;
    logic [2:0]  ImmSrc;
    logic        AluASrc;
    logic        AluBSrc;
    logic [4:0]  BrOp;
    logic [3:0]  ALUOp;
    logic        DMWr;
    logic [2:0]  DMCtrl;
    logic [1:0]  RUDataWrSrc;

    // Data paths
    logic [31:0] rs1;
    logic [31:0] rs2;
    logic [31:0] ImmExt;
    logic [31:0] MuxA;
    logic [31:0] MuxB;
    logic [31:0] Alu_out;
    logic [31:0] DataRd;
    logic [31:0] MuxRUDataWrSrc;

    // Internal summation and branch
    logic [31:0] Suma       = 32'b0;
    logic [31:0] MuxSalto   = 32'b0;
    logic        NextPCSrc;

    //------------------------------------------------------------------------------
    // Sequential PC update
    //------------------------------------------------------------------------------
    always_ff @(posedge Clk) begin
        Out_PC <= MuxSalto;
    end

    //------------------------------------------------------------------------------
    // Combinational logic: ALU inputs, immediate, multiplexers, branch
    //------------------------------------------------------------------------------
    always_comb begin
        // Increment PC by 4
        Suma = Out_PC + 4;

        // ALU A input multiplexer
        MuxA = (AluASrc) ? Out_PC : rs1;

        // ALU B input multiplexer
        MuxB = (AluBSrc) ? ImmExt : rs2;

        // Register Write Data multiplexer
        unique case (RUDataWrSrc)
            2'b10: MuxRUDataWrSrc = Suma;
            2'b01: MuxRUDataWrSrc = DataRd;
            2'b00: MuxRUDataWrSrc = Alu_out;
            default: MuxRUDataWrSrc = 32'b0;
        endcase

        // Branch target multiplexer
        MuxSalto = (NextPCSrc) ? Alu_out : Suma;
    end

    //------------------------------------------------------------------------------
    // Module instances
    //------------------------------------------------------------------------------
    Instruction_memory im (
        .Address    (Out_PC),
        .Instruction(Out_Instruction)
    );

    Control_unit cu (
        .OpCode       (Out_Instruction[6:0]),
        .Funct3       (Out_Instruction[14:12]),
        .Funct7       (Out_Instruction[31:25]),
        .RUWr         (RUWr),
        .ImmSrc       (ImmSrc),
        .AluASrc      (AluASrc),
        .AluBSrc      (AluBSrc),
        .BrOp         (BrOp),
        .ALUOp        (ALUOp),
        .DMWr         (DMWr),
        .DMCtrl       (DMCtrl),
        .RUDataWrSrc  (RUDataWrSrc)
    );

    Register_unit ru (
        .Clk      (Clk),
        .RuDataWr (MuxRUDataWrSrc),
        .Rs1      (Out_Instruction[19:15]),
        .Rs2      (Out_Instruction[24:20]),
        .Rd       (Out_Instruction[11:7]),
        .RuWr     (RUWr),
        .RuRs1    (rs1),
        .RuRs2    (rs2)
    );

    Imm_unit iu (
        .ImmIn   (Out_Instruction[31:7]),
        .ImmSrc  (ImmSrc),
        .ImmExt  (ImmExt)
    );

    ALU alu (
        .A      (MuxA),
        .B      (MuxB),
        .ALUOp  (ALUOp),
        .Alu_out(Alu_out)
    );

    Data_memory dm (
        .Address (Alu_out),
        .DataWr  (rs2),
        .DMWr    (DMWr),
        .DMCtrl  (DMCtrl),
        .DataRd  (DataRd)
    );

    Branch_unit bu (
        .In1       (rs1),
        .In2       (rs2),
        .BrOp      (BrOp),
        .NextPCSrc (NextPCSrc)
    );

endmodule

verilog-eda/testbench.sv
`timescale 1ns / 1ns

module Procesador_monociclo_tb;

    // --------------------------------------------------------------------------
    // Parámetros de simulación
    // --------------------------------------------------------------------------
    localparam integer CLK_PERIOD = 10;   // Periodo de reloj en ns
    localparam integer NUM_CYCLES = 100;  // Número de ciclos a simular

    // --------------------------------------------------------------------------
    // Señales
    // --------------------------------------------------------------------------
    logic Clk;

    // --------------------------------------------------------------------------
    // Instanciación del DUT
    // --------------------------------------------------------------------------
    Procesador_monociclo uut (
        .Clk(Clk)
    );

    // --------------------------------------------------------------------------
    // Generador de reloj
    // --------------------------------------------------------------------------
    initial begin
        Clk = 1'b0;
        forever #(CLK_PERIOD/2) Clk = ~Clk;
    end

    // --------------------------------------------------------------------------
    // Monitor de señales
    // --------------------------------------------------------------------------
    initial begin
        $display("time(ns)\tClk\tPC");
        $monitor("%0t\t%b\t%h", $time, Clk, uut.Out_PC);
    end

    // --------------------------------------------------------------------------
    // Bloque principal de simulación
    // --------------------------------------------------------------------------
    initial begin
        // Generar archivo VCD
        $dumpfile("Procesador_monociclo_tb.vcd");
        $dumpvars(0, Procesador_monociclo_tb);

        // Ejecutar simulación
        #(CLK_PERIOD * NUM_CYCLES);

        $display("Simulación completada en %0t ns", $time);
        $finish;
    end

endmodule

verilog-eda/Procesador_monociclo_tb.vcd
$date
Fri May 30 20:12:38 2025
$end
$version
Riviera-PRO Version 2023.04.112.8911
$end
$timescale
1 ns
$end

$scope module Procesador_monociclo_tb $end
$var reg 1 ! Clk $end
$var parameter 32 " CLK_PERIOD [31:0] $end
$var parameter 32 # NUM_CYCLES [31:0] $end

$scope module uut $end
$var wire 1 $ Clk $end
$var reg 32 % Out_PC [31:0] $end
$var reg 32 & Out_Instruction [31:0] $end
$var reg 1 ' RUWr $end
$var reg 3 ( ImmSrc [2:0] $end
$var reg 1 ) AluASrc $end
$var reg 1 * AluBSrc $end
$var reg 5 + BrOp [4:0] $end
$var reg 4 , ALUOp [3:0] $end
$var reg 1 - DMWr $end
$var reg 3 . DMCtrl [2:0] $end
$var reg 2 / RUDataWrSrc [1:0] $end
$var reg 32 0 rs1 [31:0] $end
$var reg 32 1 rs2 [31:0] $end
$var reg 32 2 ImmExt [31:0] $end
$var reg 32 3 MuxA [31:0] $end
$var reg 32 4 MuxB [31:0] $end
$var reg 32 5 Alu_out [31:0] $end
$var reg 32 6 DataRd [31:0] $end
$var reg 32 7 MuxRUDataWrSrc [31:0] $end
$var reg 32 8 Suma [31:0] $end
$var reg 32 9 MuxSalto [31:0] $end
$var reg 1 : NextPCSrc $end

$scope module im $end
$var wire 32 ; Address [31:0] $end
$var reg 32 < Instruction [31:0] $end
$upscope $end


$scope module cu $end
$var wire 7 = OpCode [6:0] $end
$var wire 3 > Funct3 [2:0] $end
$var wire 7 ? Funct7 [6:0] $end
$var reg 1 @ RUWr $end
$var reg 3 A ImmSrc [2:0] $end
$var reg 1 B AluASrc $end
$var reg 1 C AluBSrc $end
$var reg 5 D BrOp [4:0] $end
$var reg 4 E ALUOp [3:0] $end
$var reg 1 F DMWr $end
$var reg 3 G DMCtrl [2:0] $end
$var reg 2 H RUDataWrSrc [1:0] $end
$upscope $end


$scope module ru $end
$var wire 1 $ Clk $end
$var wire 32 I RuDataWr [31:0] $end
$var wire 5 J Rs1 [4:0] $end
$var wire 5 K Rs2 [4:0] $end
$var wire 5 L Rd [4:0] $end
$var wire 1 M RuWr $end
$var reg 32 N RuRs1 [31:0] $end
$var reg 32 O RuRs2 [31:0] $end
$upscope $end


$scope module iu $end
$var wire 25 P ImmIn [24:0] $end
$var wire 3 Q ImmSrc [2:0] $end
$var reg 32 R ImmExt [31:0] $end
$upscope $end


$scope module alu $end
$var wire 32 S A [31:0] $end
$var wire 32 T B [31:0] $end
$var wire 4 U ALUOp [3:0] $end
$var reg 32 V Alu_out [31:0] $end
$upscope $end


$scope module dm $end
$var wire 32 W Address [31:0] $end
$var wire 32 X DataWr [31:0] $end
$var wire 1 Y DMWr $end
$var wire 3 Z DMCtrl [2:0] $end
$var reg 32 [ DataRd [31:0] $end
$upscope $end


$scope module bu $end
$var wire 32 \ In1 [31:0] $end
$var wire 32 X In2 [31:0] $end
$var wire 5 ] BrOp [4:0] $end
$var reg 1 ^ NextPCSrc $end
$upscope $end

$upscope $end

$upscope $end

$enddefinitions $end
$dumpvars
0!
b1010 "
b1100100 #
0$
b0 %
b10100000000010100010011 &
1'
b0 (
0)
1*
b0 +
b0 ,
0-
b0 .
b0 /
b0 0
b0 1
b101 2
b0 3
b101 4
b101 5
b0 6
b101 7
b100 8
b100 9
0:
b0 ;
b10100000000010100010011 <
b10011 =
b0 >
b0 ?
1@
b0 A
0B
1C
b0 D
b0 E
0F
b0 G
b0 H
b101 I
b0 J
b101 K
b1010 L
1M
b0 N
b0 O
b1010000000001010 P
b0 Q
b101 R
b0 S
b101 T
b0 U
b101 V
b101 W
b0 X
0Y
b0 Z
b0 [
b0 \
b0 ]
0^
$end
#5
1!
1$
b100 %
b100 ;
b1000 8
b1000 9
b1010010011 <
b1010010011 &
b101 P
b101 L
b0 K
b0 R
b0 2
b0 4
b0 T
b0 V
b0 5
b0 W
b0 7
b0 I
#10
0!
0$
#15
1!
1$
b1000 %
b1000 ;
b1100 8
b1100 9
b100000000001100010011 <
b100000000001100010011 &
b10000000000110 P
b110 L
b1 K
b1 R
b1 2
b1 4
b1 T
b1 V
b1 5
b1 W
b1 7
b1 I
#20
0!
0$
#25
1!
1$
b1100 %
b1100 ;
b10000 8
b10000 9
b11001010100100001100011 <
b11001010100100001100011 &
b1100101010010000 P
b10000 L
b110 K
b1010 J
b100 >
b1100011 =
b110 R
b101 N
b1 O
0@
1C
b101 A
1B
b1100 D
b110 2
b101 0
b1 1
0'
b101 (
1)
b1100 +
b1100 ]
b101 Q
0M
b1 X
b101 \
b1100 3
b110 4
b10000 R
b10000 2
b110 T
b1100 S
b10000 4
b10010 V
b10010 5
b10010 W
b10000 T
b10010 7
b11100 V
b11100 5
b11100 W
b10010 I
b11100 7
b11100 I
#30
0!
0$
#35
1!
1$
b10000 %
b10000 ;
b10100 8
b10000 3
b10100 9
b11000101000001010110011 <
b11000101000001010110011 &
b1100010100000101 P
b101 L
b101 J
b0 >
b110011 =
b10000 S
b100000000100 R
b0 N
b0 A
0B
0C
b0 D
1@
b100000 V
b100000000100 2
b0 0
b0 (
0)
0*
b0 +
1'
b100000 5
b100000 W
1M
b0 ]
b0 Q
b0 \
b0 3
b1 4
b100000 7
bx [
b110 R
bx 6
b110 2
b100000 I
b1 T
b0 S
b1 V
b1 5
b1 W
b1 7
b0 [
b0 6
b1 I
#40
0!
0$
#45
1!
1$
b10100 %
b10100 ;
b11000 8
b11000 9
b1 N
b100110000001100010011 <
b1 0
b100110000001100010011 &
b10011000000110 P
b110 L
b1 K
b110 J
b10011 =
b1 \
b1 3
b1 R
b0 O
1@
1C
b1 2
b0 1
1*
b0 X
b1 S
b10 V
b10 5
b10 W
b10 7
b10 I
#50
0!
0$
#55
1!
1$
b11000 %
b11000 ;
b11100 8
b11100 9
b10 N
b11111110000000000000101011100011 <
b10 0
b11111110000000000000101011100011 &
b1111111000000000000010101 P
b10101 L
b0 K
b0 J
b1111111 ?
b1100011 =
b10 \
b10 3
b11111111111111111111111111100000 R
b0 N
0@
1C
b101 A
1B
b1000 D
b11111111111111111111111111100000 2
b0 0
0'
b101 (
1)
b1000 +
b1000 ]
b101 Q
0M
b0 \
b10 S
b11000 3
b11111111111111111111111111100000 4
1^
b11111111111111111111111111110100 R
b11 V
1:
b11111111111111111111111111110100 2
b11 5
b11 W
b11111111111111111111111111100000 T
b11000 S
b11111111111111111111111111110100 4
b11 7
b11 9
b11111111111111111111111111111000 V
b11111111111111111111111111111000 5
b11111111111111111111111111111000 W
b11 I
b11111111111111111111111111110100 T
b11111111111111111111111111111000 7
b11111111111111111111111111111000 9
bx [
b1100 V
bx 6
b1100 5
b1100 W
b11111111111111111111111111111000 I
b1100 7
b1100 9
b0 [
b0 6
b1100 I
#60
0!
0$
#65
1!
1$
b1100 %
b1100 ;
b10000 8
b1100 3
b11001010100100001100011 <
b11001010100100001100011 &
b1100101010010000 P
b10000 L
b110 K
b1010 J
b0 ?
b100 >
b1100 S
b10000 R
b101 N
b10 O
b101 A
1B
1C
b1100 D
b0 V
b10000 2
b101 0
b10 1
b1100 +
b0 5
b0 W
b1100 ]
b10 X
b101 \
b10000 4
b0 7
b0 9
0^
0:
b0 I
b10000 T
b10000 9
b11100 V
b11100 5
b11100 W
b11100 7
b11100 I
#70
0!
0$
#75
1!
1$
b10000 %
b10000 ;
b10100 8
b10000 3
b10100 9
b11000101000001010110011 <
b11000101000001010110011 &
b1100010100000101 P
b101 L
b101 J
b0 >
b110011 =
b10000 S
b100000000100 R
b1 N
b0 A
0B
0C
b0 D
1@
b100000 V
b100000000100 2
b1 0
b0 (
0)
0*
b0 +
1'
b100000 5
b100000 W
1M
b0 ]
b0 Q
b1 \
b1 3
b10 4
b100000 7
bx [
b110 R
bx 6
b110 2
b100000 I
b10 T
b1 S
b11 V
b11 5
b11 W
b11 7
b0 [
b0 6
b11 I
#80
0!
0$
#85
1!
1$
b10100 %
b10100 ;
b11000 8
b11000 9
b11 N
b100110000001100010011 <
b11 0
b100110000001100010011 &
b10011000000110 P
b110 L
b1 K
b110 J
b10011 =
b11 \
b11 3
b1 R
b10 N
b0 O
1@
1C
b1 2
b10 0
b0 1
1*
b0 X
b10 \
b11 S
b10 3
b1 4
b101 V
b101 5
b101 W
b1 T
b10 S
b101 7
b11 V
b11 5
b11 W
b101 I
b11 7
b11 I
#90
0!
0$
#95
1!
1$
b11000 %
b11000 ;
b11100 8
b11100 9
b11 N
b11111110000000000000101011100011 <
b11 0
b11111110000000000000101011100011 &
b1111111000000000000010101 P
b10101 L
b0 K
b0 J
b1111111 ?
b1100011 =
b11 \
b11 3
b11111111111111111111111111100000 R
b0 N
0@
1C
b101 A
1B
b1000 D
b11111111111111111111111111100000 2
b0 0
0'
b101 (
1)
b1000 +
b1000 ]
b101 Q
0M
b0 \
b11 S
b11000 3
b11111111111111111111111111100000 4
1^
b11111111111111111111111111110100 R
b100 V
1:
b11111111111111111111111111110100 2
b100 5
b100 W
b11111111111111111111111111100000 T
b11000 S
b11111111111111111111111111110100 4
b100 7
b100 9
b11111111111111111111111111111000 V
b11111111111111111111111111111000 5
b11111111111111111111111111111000 W
b100 I
b11111111111111111111111111110100 T
b11111111111111111111111111111000 7
b11111111111111111111111111111000 9
bx [
b1100 V
bx 6
b1100 5
b1100 W
b11111111111111111111111111111000 I
b1100 7
b1100 9
b0 [
b0 6
b1100 I
#100
0!
0$
#105
1!
1$
b1100 %
b1100 ;
b10000 8
b1100 3
b11001010100100001100011 <
b11001010100100001100011 &
b1100101010010000 P
b10000 L
b110 K
b1010 J
b0 ?
b100 >
b1100 S
b10000 R
b101 N
b11 O
b101 A
1B
1C
b1100 D
b0 V
b10000 2
b101 0
b11 1
b1100 +
b0 5
b0 W
b1100 ]
b11 X
b101 \
b10000 4
b0 7
b0 9
0^
0:
b0 I
b10000 T
b10000 9
b11100 V
b11100 5
b11100 W
b11100 7
b11100 I
#110
0!
0$
#115
1!
1$
b10000 %
b10000 ;
b10100 8
b10000 3
b10100 9
b11000101000001010110011 <
b11000101000001010110011 &
b1100010100000101 P
b101 L
b101 J
b0 >
b110011 =
b10000 S
b100000000100 R
b11 N
b0 A
0B
0C
b0 D
1@
b100000 V
b100000000100 2
b11 0
b0 (
0)
0*
b0 +
1'
b100000 5
b100000 W
1M
b0 ]
b0 Q
b11 \
b11 3
b11 4
b100000 7
bx [
b110 R
bx 6
b110 2
b100000 I
b11 T
b11 S
b110 V
b110 5
b110 W
b110 7
b0 [
b0 6
b110 I
#120
0!
0$
#125
1!
1$
b10100 %
b10100 ;
b11000 8
b11000 9
b110 N
b100110000001100010011 <
b110 0
b100110000001100010011 &
b10011000000110 P
b110 L
b1 K
b110 J
b10011 =
b110 \
b110 3
b1 R
b11 N
b0 O
1@
1C
b1 2
b11 0
b0 1
1*
b0 X
b11 \
b110 S
b11 3
b1 4
b1001 V
b1001 5
b1001 W
b1 T
b11 S
b1001 7
b100 V
b100 5
b100 W
b1001 I
b100 7
b100 I
#130
0!
0$
#135
1!
1$
b11000 %
b11000 ;
b11100 8
b11100 9
b100 N
b11111110000000000000101011100011 <
b100 0
b11111110000000000000101011100011 &
b1111111000000000000010101 P
b10101 L
b0 K
b0 J
b1111111 ?
b1100011 =
b100 \
b100 3
b11111111111111111111111111100000 R
b0 N
0@
1C
b101 A
1B
b1000 D
b11111111111111111111111111100000 2
b0 0
0'
b101 (
1)
b1000 +
b1000 ]
b101 Q
0M
b0 \
b100 S
b11000 3
b11111111111111111111111111100000 4
1^
b11111111111111111111111111110100 R
b101 V
1:
b11111111111111111111111111110100 2
b101 5
b101 W
b11111111111111111111111111100000 T
b11000 S
b11111111111111111111111111110100 4
b101 7
b101 9
b11111111111111111111111111111000 V
b11111111111111111111111111111000 5
b11111111111111111111111111111000 W
b101 I
b11111111111111111111111111110100 T
b11111111111111111111111111111000 7
b11111111111111111111111111111000 9
bx [
b1100 V
bx 6
b1100 5
b1100 W
b11111111111111111111111111111000 I
b1100 7
b1100 9
b0 [
b0 6
b1100 I
#140
0!
0$
#145
1!
1$
b1100 %
b1100 ;
b10000 8
b1100 3
b11001010100100001100011 <
b11001010100100001100011 &
b1100101010010000 P
b10000 L
b110 K
b1010 J
b0 ?
b100 >
b1100 S
b10000 R
b101 N
b100 O
b101 A
1B
1C
b1100 D
b0 V
b10000 2
b101 0
b100 1
b1100 +
b0 5
b0 W
b1100 ]
b100 X
b101 \
b10000 4
b0 7
b0 9
0^
0:
b0 I
b10000 T
b10000 9
b11100 V
b11100 5
b11100 W
b11100 7
b11100 I
#150
0!
0$
#155
1!
1$
b10000 %
b10000 ;
b10100 8
b10000 3
b10100 9
b11000101000001010110011 <
b11000101000001010110011 &
b1100010100000101 P
b101 L
b101 J
b0 >
b110011 =
b10000 S
b100000000100 R
b110 N
b0 A
0B
0C
b0 D
1@
b100000 V
b100000000100 2
b110 0
b0 (
0)
0*
b0 +
1'
b100000 5
b100000 W
1M
b0 ]
b0 Q
b110 \
b110 3
b100 4
b100000 7
bx [
b110 R
bx 6
b110 2
b100000 I
b100 T
b110 S
b1010 V
b1010 5
b1010 W
b1010 7
b0 [
b0 6
b1010 I
#160
0!
0$
