procesador/otros/Verilog/Modules/Branch Unit/BranchUnit.sv
module BranchUnit (
    input logic [31:0] o_rs1,        // Entrada de fuente rs1Out
    input logic [31:0] o_rs2,        // Entrada de fuente rs2Out
    input logic [4:0] BrOp,            // Señal de operación de branch
    output logic NextPCSrc             // Señal para seleccionar la siguiente dirección del PC
);

    always @(*) begin
        case (BrOp)
            5'b01000: NextPCSrc = (o_rs1 == o_rs2);  // BEQ: Igualdad
            5'b01001: NextPCSrc = (o_rs1 != o_rs2);  // BNE: Diferencia
            5'b01100: NextPCSrc = ($signed(o_rs1) < $signed(o_rs2));  // BLT: Menor que (con signo)
            5'b01101: NextPCSrc = ($signed(o_rs1) >= $signed(o_rs2)); // BGE: Mayor o igual que (con signo)
            5'b01110: NextPCSrc = (o_rs1 < o_rs2);   // BLT: Menor que (sin signo)
            5'b01111: NextPCSrc = (o_rs1 >= o_rs2);  // BGE: Mayor o igual que (sin signo)
            5'b1xxxx: NextPCSrc = 1'b1;
            default:  NextPCSrc = 1'b0;  // Por defecto no hay salto
        endcase
    end
endmodule

procesador/otros/Verilog/Modules/Branch Unit/BU_tb.sv
`include "BranchUnit.sv"

module BU_tb;

    // Definición de las señales de entrada y salida
    logic [31:0] o_rs1;
    logic [31:0] o_rs2;
    logic [4:0] BrOp;
    logic NextPCSrc;

    // Instancia del módulo BranchUnit
    BranchUnit bu (
        .o_rs1(o_rs1),
        .o_rs2(o_rs2),
        .BrOp(BrOp),
        .NextPCSrc(NextPCSrc)
    );

    // Proceso inicial para aplicar los estímulos
    initial begin
        $dumpfile("BU.vcd");
        $dumpvars(0, BU_tb);

        // Caso de prueba 1: BEQ (Branch if Equal)
        o_rs1 = 32'd10;
        o_rs2 = 32'd5;
        BrOp = 5'b01000; // BEQ
        #10; // Esperar 10 unidades de tiempo
        $display("BEQ: o_rs1 = %d, o_rs2 = %d, NextPCSrc = %b", o_rs1, o_rs2, NextPCSrc);

        // Caso de prueba 2: BNE (Branch if Not Equal)
        o_rs1 = 32'd15;
        o_rs2 = 32'd15;
        BrOp = 5'b01001; // BNE
        #10; // Esperar 10 unidades de tiempo
        $display("BNE: o_rs1 = %d, o_rs2 = %d, NextPCSrc = %b", o_rs1, o_rs2, NextPCSrc);

        // Caso de prueba 3: BLT (Branch if Less Than, signed)
        o_rs1 = 32'd5;
        o_rs2 = 32'd4;
        BrOp = 5'b01100; // BLT
        #10; // Esperar 10 unidades de tiempo
        $display("BLT: o_rs1 = %d, o_rs2 = %d, NextPCSrc = %b", o_rs1, o_rs2, NextPCSrc);

        // Caso de prueba 4: BGE (Branch if Greater or Equal, signed)
        o_rs1 = 32'd15;
        o_rs2 = 32'd32;
        BrOp = 5'b01101; // BGE
        #10; // Esperar 10 unidades de tiempo
        $display("BGE: o_rs1 = %d, o_rs2 = %d, NextPCSrc = %b", o_rs1, o_rs2, NextPCSrc);

        // Caso de prueba 5: BLTU (Branch if Less Than, unsigned)
        o_rs1 = 32'd5;
        o_rs2 = 32'd10;
        BrOp = 5'b01110; // BLTU
        #10; // Esperar 10 unidades de tiempo
        $display("BLTU: o_rs1 = %d, o_rs2 = %d, NextPCSrc = %b", o_rs1, o_rs2, NextPCSrc);

        // Caso de prueba 6: BGEU (Branch if Greater or Equal, unsigned)
        o_rs1 = 32'd10;
        o_rs2 = 32'd5;
        BrOp = 5'b01111; // BGEU
        #10; // Esperar 10 unidades de tiempo
        $display("BGEU: o_rs1 = %d, o_rs2 = %d, NextPCSrc = %b", o_rs1, o_rs2, NextPCSrc);

        // Caso de prueba 7: Caso por defecto
        o_rs1 = 32'd0;
        o_rs2 = 32'd0;
        BrOp = 5'b00000; // Caso por defecto
        #10; // Esperar 10 unidades de tiempo
        $display("Default: o_rs1 = %d, o_rs2 = %d, NextPCSrc = %b", o_rs1, o_rs2, NextPCSrc);
        

        // Terminar la simulación
        $finish;
    end
endmodule

procesador/otros/Verilog/Modules/Branch Unit/BU.vcd
$date
	Wed Oct 30 15:07:32 2024
$end
$version
	Icarus Verilog
$end
$timescale
	1s
$end
$scope module BU_tb $end
$var wire 1 ! NextPCSrc $end
$var reg 5 " BrOp [4:0] $end
$var reg 32 # o_rs1 [31:0] $end
$var reg 32 $ o_rs2 [31:0] $end
$scope module bu $end
$var wire 5 % BrOp [4:0] $end
$var wire 32 & o_rs1 [31:0] $end
$var wire 32 ' o_rs2 [31:0] $end
$var reg 1 ! NextPCSrc $end
$upscope $end
$upscope $end
$enddefinitions $end
#0
$dumpvars
b101 '
b1010 &
b1000 %
b101 $
b1010 #
b1000 "
0!
$end
#10
b1001 "
b1001 %
b1111 $
b1111 '
b1111 #
b1111 &
#20
b1100 "
b1100 %
b100 $
b100 '
b101 #
b101 &
#30
b1101 "
b1101 %
b100000 $
b100000 '
b1111 #
b1111 &
#40
1!
b1110 "
b1110 %
b1010 $
b1010 '
b101 #
b101 &
#50
b1111 "
b1111 %
b101 $
b101 '
b1010 #
b1010 &
#60
x!
b0 "
b0 %
b0 $
b0 '
b0 #
b0 &
#70
0!
b1110 "
b1110 %
b1010 $
b1010 '
b11111111111111111111111111111011 #
b11111111111111111111111111111011 &
#80
1!
b1100 "
b1100 %
b0 $
b0 '
